Cong0KaishiXueJiagouLiyunhuaWan/README.md
Cong0KaishiXueJiagouLiyunhuaWan/__init__.py
Cong0KaishiXueJiagouLiyunhuaWan/__main__.py
Cong0KaishiXueJiagouLiyunhuaWan/file.epub
Cong0KaishiXueJiagouLiyunhuaWan/index.html
Cong0KaishiXueJiagouLiyunhuaWan/css/__init__.py
Cong0KaishiXueJiagouLiyunhuaWan/css/annotations.css
Cong0KaishiXueJiagouLiyunhuaWan/css/main.css
Cong0KaishiXueJiagouLiyunhuaWan/css/normalize.css
Cong0KaishiXueJiagouLiyunhuaWan/css/popup.css
Cong0KaishiXueJiagouLiyunhuaWan/font/__init__.py
Cong0KaishiXueJiagouLiyunhuaWan/font/fontello.eot
Cong0KaishiXueJiagouLiyunhuaWan/font/fontello.svg
Cong0KaishiXueJiagouLiyunhuaWan/font/fontello.ttf
Cong0KaishiXueJiagouLiyunhuaWan/font/fontello.woff
Cong0KaishiXueJiagouLiyunhuaWan/img/__init__.py
Cong0KaishiXueJiagouLiyunhuaWan/img/annotator-glyph-sprite.png
Cong0KaishiXueJiagouLiyunhuaWan/img/annotator-icon-sprite.png
Cong0KaishiXueJiagouLiyunhuaWan/img/apple-touch-icon.png
Cong0KaishiXueJiagouLiyunhuaWan/img/cancelfullscreen.png
Cong0KaishiXueJiagouLiyunhuaWan/img/close.png
Cong0KaishiXueJiagouLiyunhuaWan/img/fullscreen.png
Cong0KaishiXueJiagouLiyunhuaWan/img/loader.gif
Cong0KaishiXueJiagouLiyunhuaWan/img/menu-icon.png
Cong0KaishiXueJiagouLiyunhuaWan/img/save.png
Cong0KaishiXueJiagouLiyunhuaWan/img/saved.png
Cong0KaishiXueJiagouLiyunhuaWan/img/settings-s.png
Cong0KaishiXueJiagouLiyunhuaWan/img/settings.png
Cong0KaishiXueJiagouLiyunhuaWan/img/star.png
Cong0KaishiXueJiagouLiyunhuaWan/js/__init__.py
Cong0KaishiXueJiagouLiyunhuaWan/js/epub.js
Cong0KaishiXueJiagouLiyunhuaWan/js/epub.min.js
Cong0KaishiXueJiagouLiyunhuaWan/js/epub.min.map
Cong0KaishiXueJiagouLiyunhuaWan/js/hooks.min.js
Cong0KaishiXueJiagouLiyunhuaWan/js/hooks.min.map
Cong0KaishiXueJiagouLiyunhuaWan/js/reader.js
Cong0KaishiXueJiagouLiyunhuaWan/js/reader.js.map
Cong0KaishiXueJiagouLiyunhuaWan/js/reader.min.js
Cong0KaishiXueJiagouLiyunhuaWan/js/reader.min.map
Cong0KaishiXueJiagouLiyunhuaWan/js/hooks/__init__.py
cong_0_kaishi_xue_jiagou_liyunhua_wan-2024.3.3.0.dist-info/METADATA
cong_0_kaishi_xue_jiagou_liyunhua_wan-2024.3.3.0.dist-info/WHEEL
cong_0_kaishi_xue_jiagou_liyunhua_wan-2024.3.3.0.dist-info/entry_points.txt
cong_0_kaishi_xue_jiagou_liyunhua_wan-2024.3.3.0.dist-info/top_level.txt
cong_0_kaishi_xue_jiagou_liyunhua_wan-2024.3.3.0.dist-info/RECORD
